odoo/addons/account_invoice_refund_link/README.rst
odoo/addons/account_invoice_refund_link/__init__.py
odoo/addons/account_invoice_refund_link/__manifest__.py
odoo/addons/account_invoice_refund_link/hooks.py
odoo/addons/account_invoice_refund_link/i18n/account_invoice_refund_link.pot
odoo/addons/account_invoice_refund_link/i18n/ar.po
odoo/addons/account_invoice_refund_link/i18n/bg.po
odoo/addons/account_invoice_refund_link/i18n/bs.po
odoo/addons/account_invoice_refund_link/i18n/ca.po
odoo/addons/account_invoice_refund_link/i18n/cs.po
odoo/addons/account_invoice_refund_link/i18n/da.po
odoo/addons/account_invoice_refund_link/i18n/de.po
odoo/addons/account_invoice_refund_link/i18n/el_GR.po
odoo/addons/account_invoice_refund_link/i18n/en_GB.po
odoo/addons/account_invoice_refund_link/i18n/es.po
odoo/addons/account_invoice_refund_link/i18n/es_AR.po
odoo/addons/account_invoice_refund_link/i18n/es_BO.po
odoo/addons/account_invoice_refund_link/i18n/es_CL.po
odoo/addons/account_invoice_refund_link/i18n/es_CO.po
odoo/addons/account_invoice_refund_link/i18n/es_CR.po
odoo/addons/account_invoice_refund_link/i18n/es_DO.po
odoo/addons/account_invoice_refund_link/i18n/es_EC.po
odoo/addons/account_invoice_refund_link/i18n/es_ES.po
odoo/addons/account_invoice_refund_link/i18n/es_MX.po
odoo/addons/account_invoice_refund_link/i18n/es_PE.po
odoo/addons/account_invoice_refund_link/i18n/es_PY.po
odoo/addons/account_invoice_refund_link/i18n/es_VE.po
odoo/addons/account_invoice_refund_link/i18n/et.po
odoo/addons/account_invoice_refund_link/i18n/eu.po
odoo/addons/account_invoice_refund_link/i18n/eu_ES.po
odoo/addons/account_invoice_refund_link/i18n/fa.po
odoo/addons/account_invoice_refund_link/i18n/fi.po
odoo/addons/account_invoice_refund_link/i18n/fr.po
odoo/addons/account_invoice_refund_link/i18n/fr_CA.po
odoo/addons/account_invoice_refund_link/i18n/fr_CH.po
odoo/addons/account_invoice_refund_link/i18n/fr_FR.po
odoo/addons/account_invoice_refund_link/i18n/gl.po
odoo12_addon_account_invoice_refund_link-12.0.1.0.0.99.dev8.dist-info/METADATA
odoo12_addon_account_invoice_refund_link-12.0.1.0.0.99.dev8.dist-info/WHEEL
odoo12_addon_account_invoice_refund_link-12.0.1.0.0.99.dev8.dist-info/top_level.txt
odoo12_addon_account_invoice_refund_link-12.0.1.0.0.99.dev8.dist-info/RECORD
